<?xml version="1.0" encoding="GB2312"?><Setting Version="1.0"><Column displayname="!" width="113" visible="False" enable="true" type="TextCellType" sort="False" zoomFactor="1.2" HorizontalAlignment="General"></Column><Column displayname="期效" width="113" visible="False" enable="true" type="TextCellType" sort="False" zoomFactor="1.2" HorizontalAlignment="General"></Column><Column displayname="医嘱类型" width="63" visible="True" enable="true" type="TextCellType" sort="False" zoomFactor="1.2" HorizontalAlignment="General"></Column><Column displayname="医嘱流水号" width="113" visible="False" enable="true" type="TextCellType" sort="False" zoomFactor="1.2" HorizontalAlignment="General"></Column><Column displayname="医嘱状态" width="113" visible="False" enable="true" type="TextCellType" sort="False" zoomFactor="1.2" HorizontalAlignment="General"></Column><Column displayname="组合号" width="113" visible="False" enable="true" type="TextCellType" sort="False" zoomFactor="1.2" HorizontalAlignment="General"></Column><Column displayname="主药" width="113" visible="False" enable="true" type="TextCellType" sort="False" zoomFactor="1.2" HorizontalAlignment="General"></Column><Column displayname="组号" width="20" visible="True" enable="true" type="TextCellType" sort="False" zoomFactor="1.2" HorizontalAlignment="General"></Column><Column displayname="开立时间" width="112" visible="True" enable="true" type="TextCellType" sort="False" zoomFactor="1.2" HorizontalAlignment="General"></Column><Column displayname="开立医生" width="63" visible="True" enable="true" type="TextCellType" sort="False" zoomFactor="1.2" HorizontalAlignment="General"></Column><Column displayname="顺序号" width="79" visible="False" enable="true" type="NumberCellType" sort="False" zoomFactor="1.2" DecimalPlaces="0" HorizontalAlignment="General"></Column><Column displayname="医嘱名称" width="234" visible="True" enable="true" type="TextCellType" sort="False" zoomFactor="1.2" HorizontalAlignment="General"></Column><Column displayname="组" width="24" visible="True" enable="true" type="TextCellType" sort="False" zoomFactor="1.2" HorizontalAlignment="General"></Column><Column displayname="首日量" width="40" visible="True" enable="true" type="NumberCellType" sort="False" zoomFactor="1.2" DecimalPlaces="0" HorizontalAlignment="General"></Column><Column displayname="每次用量" width="44" visible="True" enable="true" type="TextCellType" sort="False" zoomFactor="1.2" HorizontalAlignment="General"></Column><Column displayname="单位" width="30" visible="True" enable="true" type="TextCellType" sort="False" zoomFactor="1.2" HorizontalAlignment="General"></Column><Column displayname="频次" width="30" visible="True" enable="true" type="TextCellType" sort="False" zoomFactor="1.2" HorizontalAlignment="General"></Column><Column displayname="频次名称" width="113" visible="False" enable="true" type="TextCellType" sort="False" zoomFactor="1.2" HorizontalAlignment="General"></Column><Column displayname="用法编码" width="113" visible="False" enable="true" type="TextCellType" sort="False" zoomFactor="1.2" HorizontalAlignment="General"></Column><Column displayname="用法" width="54" visible="True" enable="true" type="TextCellType" sort="False" zoomFactor="1.2" HorizontalAlignment="General"></Column><Column displayname="总量" width="39" visible="True" enable="true" type="TextCellType" sort="False" zoomFactor="1.2" HorizontalAlignment="General"></Column><Column displayname="总量单位" width="37" visible="True" enable="true" type="TextCellType" sort="False" zoomFactor="1.2" HorizontalAlignment="General"></Column><Column displayname="付数" width="113" visible="False" enable="true" type="TextCellType" sort="False" zoomFactor="1.2" HorizontalAlignment="General"></Column><Column displayname="系统类别" width="63" visible="True" enable="true" type="TextCellType" sort="False" zoomFactor="1.2" HorizontalAlignment="General"></Column><Column displayname="开始时间" width="111" visible="True" enable="true" type="TextCellType" sort="False" zoomFactor="1.2" HorizontalAlignment="General"></Column><Column displayname="结束时间" width="111" visible="True" enable="true" type="TextCellType" sort="False" zoomFactor="1.2" HorizontalAlignment="General"></Column><Column displayname="停止时间" width="111" visible="True" enable="true" type="TextCellType" sort="False" zoomFactor="1.2" HorizontalAlignment="General"></Column><Column displayname="执行科室编码" width="113" visible="False" enable="true" type="TextCellType" sort="False" zoomFactor="1.2" HorizontalAlignment="General"></Column><Column displayname="执行科室" width="98" visible="True" enable="true" type="TextCellType" sort="False" zoomFactor="1.2" HorizontalAlignment="General"></Column><Column displayname="急" width="18" visible="True" enable="true" type="CheckBoxCellType" sort="False" zoomFactor="1.2" HorizontalAlignment="General"></Column><Column displayname="检查部位" width="113" visible="False" enable="true" type="TextCellType" sort="False" zoomFactor="1.2" HorizontalAlignment="General"></Column><Column displayname="样本类型" width="113" visible="False" enable="true" type="TextCellType" sort="False" zoomFactor="1.2" HorizontalAlignment="General"></Column><Column displayname="取药药房编码" width="113" visible="False" enable="true" type="TextCellType" sort="False" zoomFactor="1.2" HorizontalAlignment="General"></Column><Column displayname="取药药房" width="63" visible="True" enable="true" type="TextCellType" sort="False" zoomFactor="1.2" HorizontalAlignment="General"></Column><Column displayname="备注" width="98" visible="True" enable="true" type="TextCellType" sort="False" zoomFactor="1.2" HorizontalAlignment="General"></Column><Column displayname="录入人编码" width="113" visible="False" enable="true" type="TextCellType" sort="False" zoomFactor="1.2" HorizontalAlignment="General"></Column><Column displayname="录入人" width="113" visible="False" enable="true" type="TextCellType" sort="False" zoomFactor="1.2" HorizontalAlignment="General"></Column><Column displayname="开立科室" width="63" visible="True" enable="true" type="TextCellType" sort="False" zoomFactor="1.2" HorizontalAlignment="General"></Column><Column displayname="停止人编码" width="113" visible="False" enable="true" type="TextCellType" sort="False" zoomFactor="1.2" HorizontalAlignment="General"></Column><Column displayname="停止人" width="50" visible="True" enable="true" type="TextCellType" sort="False" zoomFactor="1.2" HorizontalAlignment="General"></Column></Setting>